cronably/__init__.py
cronably/cronably_main.py
cronably/actions/__init__.py
cronably/actions/actions.py
cronably/actions/main_action.py
cronably/actions/main_action/__init__.py
cronably/actions/main_action/capturing.py
cronably/actions/main_action/main_action.py
cronably/actions/post_action/__init__.py
cronably/actions/post_action/post_action.py
cronably/actions/post_action/report_builder.py
cronably/actions/pre_action/__init__.py
cronably/actions/pre_action/parameters.py
cronably/actions/pre_action/pre_action_validations.py
cronably/actions/pre_action/pre_actions.py
cronably/actions/repetition/__init__.py
cronably/actions/repetition/base_repetition.py
cronably/actions/repetition/daily_repetition.py
cronably/actions/repetition/repetition_factory.py
cronably/actions/repetition/std_repetition.py
cronably/actions/repetition/weekly_repetition.py
cronably/context/__init__.py
cronably/context/context.py
cronably/model/__init__.py
cronably/model/job.py
cronably/model/task.py
cronably/repositories/__init__.py
cronably/repositories/db_manager.py
cronably/repositories/job_repository.py
cronably/repositories/repository.py
cronably/repositories/task_repository.py
cronably/utils/__init__.py
cronably/utils/cronably_exception.py
cronably-1.3.1.dist-info/LICENCE.txt
cronably-1.3.1.dist-info/METADATA
cronably-1.3.1.dist-info/WHEEL
cronably-1.3.1.dist-info/top_level.txt
cronably-1.3.1.dist-info/RECORD
