Metadata-Version: 2.1
Name: cronably
Version: 1.3.1
Summary: Cronably allows you run python scripts with configured repetitions easily
Home-page: https://gitlab.com/Kotlirevsky/cronably
Author: David Kotlirevsky
Author-email: david.kotlirevsky@gmail.com
License: MIT
Keywords: cronably,cron
Platform: UNKNOWN
Classifier: License :: OSI Approved :: MIT License
Classifier: Programming Language :: Python :: 2.7
